itrigamma-0.1.0a2.dist-info/RECORD
itrigamma-0.1.0a2.dist-info/WHEEL
itrigamma-0.1.0a2.dist-info/top_level.txt
itrigamma-0.1.0a2.dist-info/METADATA
itrigamma-0.1.0a2.dist-info/licenses/LICENSE
itrigamma/__init__.py
itrigamma/citrigamma.cpython-313-darwin.so
