Metadata-Version: 2.4
Name: itrigamma
Version: 0.1.0a2
Summary: A dedicated inverse-trigamma function implementation over positive reals
Author: Nolan Hamilton
Requires-Python: >=3.9
License-File: LICENSE
Requires-Dist: numpy>=2.0
Requires-Dist: cython>=3.0
Requires-Dist: setuptools>=68
Requires-Dist: build>=1.0.0
Dynamic: license-file
